Raylib/__init__.py
Raylib/routines.py
scopylib-0.0.1.dist-info/LICENSE
scopylib-0.0.1.dist-info/METADATA
scopylib-0.0.1.dist-info/WHEEL
scopylib-0.0.1.dist-info/top_level.txt
scopylib-0.0.1.dist-info/RECORD
