Metadata-Version: 2.1
Name: scopylib
Version: 0.0.1
Summary: Show Image Library
Author-email: Raymond Li <ruifeng2002@gmail.com>
Classifier: Programming Language :: Python :: 3
Classifier: License :: OSI Approved :: MIT License
Classifier: Operating System :: OS Independent
Requires-Python: >=3.7
License-File: LICENSE
